setRegionGerbs.py
setRegionGerbs-0.2.0.dist-info/LICENSE
setRegionGerbs-0.2.0.dist-info/METADATA
setRegionGerbs-0.2.0.dist-info/WHEEL
setRegionGerbs-0.2.0.dist-info/top_level.txt
setRegionGerbs-0.2.0.dist-info/RECORD
