Metadata-Version: 2.2
Name: setRegionGerbs
Version: 0.2.0
Summary: A module to download region flags (gerbs) based on ISO codes
Home-page: https://github.com/Tato1999
Author: Tarieli Tabatadze
Author-email: tato.tabatadze.1999@gmail.com
Classifier: Programming Language :: Python :: 3
Classifier: License :: OSI Approved :: MIT License
Classifier: Operating System :: OS Independent
Requires-Python: >=3.6
License-File: LICENSE
Requires-Dist: requests
Dynamic: author
Dynamic: author-email
Dynamic: classifier
Dynamic: description-content-type
Dynamic: home-page
Dynamic: requires-dist
Dynamic: requires-python
Dynamic: summary
